{
  "file_name": "README.md",
  "file_path": "C:\\Users\\lyndz\\Downloads\\hypercode PROJECT\\hypercode\\docs\\getting-started\\README.md",
  "file_size": 551,
  "created": "2025-12-04T00:09:22.695939",
  "modified": "2025-12-04T00:09:22.697458",
  "file_type": "code",
  "content_hash": "ca6a8ebee478e78a09a4d06418a6edd1",
  "content_type": "markdown",
  "content": "# Getting Started\n\nThis directory contains guides and resources to help you get started with HyperCode.\n\n## What's Here\n\n- **Installation guides** - How to set up HyperCode on your system\n- **Quick start tutorials** - Get up and running quickly\n- **First steps** - Your first HyperCode program\n- **Development environment setup** - Configure your IDE and tools\n\n## Next Steps\n\n1. Check out the [installation guide](INSTALL.md)\n2. Try the [quick start tutorial](quickstart-checklist.md)\n3. Explore the [examples](../examples) directory",
  "metadata": {
    "headers": [
      "Getting Started",
      "What's Here",
      "Next Steps"
    ]
  },
  "relative_path": "docs\\getting-started\\README.md",
  "id": "235d6ff29542c62fcff887d05e899cb4"
}